jutest/__init__.py
jutest/jutest.py
jutest/settings.py
jutest/shortcuts.py
jutest/actions/__init__.py
jutest/actions/contains.py
jutest/actions/info.py
jutest/actions/load.py
jutest/actions/show_duplicates.py
jutest/actions/show_encodings.py
jutest/actions/show_nulls.py
jutest/actions/show_outliers.py
jutest/actions/show_popularity.py
jutest/actions/show_values.py
jutest/encode/__init__.py
jutest/encode/checker.py
jutest/encode/encode.py
jutest/utils/__init__.py
jutest/utils/choice.py
jutest/utils/display.py
jutest/utils/format_dataframe.py
jutest/utils/isnan.py
jutest-1.1.0.dist-info/METADATA
jutest-1.1.0.dist-info/WHEEL
jutest-1.1.0.dist-info/top_level.txt
jutest-1.1.0.dist-info/RECORD
